README.md
setup.cfg
setup.py
ioex/__init__.py
ioex/calcex.py
ioex/classex.py
ioex/cursesex.py
ioex/datetimeex.py
ioex/reex.py
ioex/shell.py
ioex.egg-info/PKG-INFO
ioex.egg-info/SOURCES.txt
ioex.egg-info/dependency_links.txt
ioex.egg-info/requires.txt
ioex.egg-info/top_level.txt
scripts/reyaml
scripts/select-line