Metadata-Version: 1.1
Name: ioex
Version: 0.18.0
Summary: extension for python's build-in input / output interface
Home-page: https://github.com/fphammerle/ioex
Author: Fabian Peter Hammerle
Author-email: fabian.hammerle@gmail.com
License: UNKNOWN
Download-URL: https://github.com/fphammerle/ioex/tarball/0.17.0
Platform: UNKNOWN
